neutrinoclient
