Metadata-Version: 1.0
Name: python-neutrinoclient
Version: 0.1.4
Summary: Neutrino API Client Library
Home-page: UNKNOWN
Author: Adrian Moreno
Author-email: adrian.moreno@emc.com
License: UNKNOWN
Keywords: neutrino,openstack
Platform: UNKNOWN
